finopsmetrics/__init__.py
finopsmetrics/cli.py
finopsmetrics/config/__init__.py
finopsmetrics/config/local_config.py
finopsmetrics/database/__init__.py
finopsmetrics/database/database_manager.py
finopsmetrics/iac/__init__.py
finopsmetrics/iac/client.py
finopsmetrics/iac/provider.py
finopsmetrics/iac/resources.py
finopsmetrics/iac/terraform_generator.py
finopsmetrics/ml/__init__.py
finopsmetrics/ml/anomaly_detector.py
finopsmetrics/ml/cost_predictor.py
finopsmetrics/ml/pattern_recognition.py
finopsmetrics/multicloud/__init__.py
finopsmetrics/multicloud/cloud_provider.py
finopsmetrics/multicloud/cost_comparator.py
finopsmetrics/multicloud/optimizer.py
finopsmetrics/observability/__init__.py
finopsmetrics/observability/ai_recommendations.py
finopsmetrics/observability/alerting_engine.py
finopsmetrics/observability/cost_configuration.py
finopsmetrics/observability/cost_observatory.py
finopsmetrics/observability/cost_reporting.py
finopsmetrics/observability/distributed_telemetry.py
finopsmetrics/observability/finops_dashboards.py
finopsmetrics/observability/hardware_recommendations.py
finopsmetrics/observability/infrastructure_automation.py
finopsmetrics/observability/infrastructure_dashboard.py
finopsmetrics/observability/intelligent_recommendations.py
finopsmetrics/observability/llm_config.py
finopsmetrics/observability/llm_dashboards.py
finopsmetrics/observability/llm_observability.py
finopsmetrics/observability/model_cost_attribution.py
finopsmetrics/observability/observability_hub.py
finopsmetrics/observability/performance_dashboard.py
finopsmetrics/observability/persistence.py
finopsmetrics/observability/scaling_recommendations.py
finopsmetrics/observability/security_monitor.py
finopsmetrics/observability/service_mesh.py
finopsmetrics/observability/system_monitor.py
finopsmetrics/observability/telemetry_control_tower.py
finopsmetrics/observability/telemetry_server.py
finopsmetrics/observability/vizly_chart_integration.py
finopsmetrics/plugins/__init__.py
finopsmetrics-0.3.1.dist-info/licenses/LICENSE
finopsmetrics-0.3.1.dist-info/METADATA
finopsmetrics-0.3.1.dist-info/WHEEL
finopsmetrics-0.3.1.dist-info/entry_points.txt
finopsmetrics-0.3.1.dist-info/top_level.txt
finopsmetrics-0.3.1.dist-info/RECORD
